drf-jwt-wechat/__init__.py
drf-jwt-wechat/views.py
drf_jwt_wechat/__init__.py
drf_jwt_wechat/views.py
drf_jwt_wechat-1.11.9.dist-info/LICENSE
drf_jwt_wechat-1.11.9.dist-info/METADATA
drf_jwt_wechat-1.11.9.dist-info/WHEEL
drf_jwt_wechat-1.11.9.dist-info/top_level.txt
drf_jwt_wechat-1.11.9.dist-info/RECORD
