Metadata-Version: 2.1
Name: drf-jwt-wechat
Version: 1.11.9
Summary: JSON Web Token based authentication for Django REST framework,this use to WeChat applet (小程序使用jwt）
Home-page: https://github.com/liazylee/drf-jwt-wechat
Author: liazylee
Author-email: li233111@gmail.com
License: MIT
Platform: UNKNOWN
Classifier: Development Status :: 5 - Production/Stable
Classifier: Environment :: Web Environment
Classifier: Framework :: Django
Classifier: Intended Audience :: Developers
Classifier: License :: OSI Approved :: MIT License
Classifier: Operating System :: OS Independent
Classifier: Programming Language :: Python
Classifier: Programming Language :: Python :: 2
Classifier: Programming Language :: Python :: 2.7
Classifier: Programming Language :: Python :: 3
Classifier: Programming Language :: Python :: 3.3
Classifier: Programming Language :: Python :: 3.4
Classifier: Programming Language :: Python :: 3.5
Classifier: Programming Language :: Python :: 3.6
Classifier: Topic :: Internet :: WWW/HTTP
Requires-Dist: PyJWT (<2.0.0,>=1.5.2)
Requires-Dist: djangorestframework-jwt (>=1.11.0)
Requires-Dist: requests
